{
  "snow.ai.AIActionStateDataPl": {
    "_Protection": false,
    "_Intercept": false,
    "_Conditions": [
      {
        "IsNot": false
      },
      {
        "IsNot": false
      },
      {
        "IsNot": true
      },
      {
        "IsNot": false
      }
    ],
    "_ContinuousConditions": [],
    "_Tasks": [
      {
        "_OrderPostionType": 10,
        "_ArriveRange": 4.0,
        "_MoveType": 3,
        "_MoveContinueTimes": 1,
        "_EnableDashForGunnerWeaponOn": false,
        "_AppraochCareEnable": false,
        "_AvoidNaviObstaclePerformanceUp": false,
        "_TakeRouteCloserToCircle": false,
        "_UseNaviTarget": false
      },
      {
        "_SubType": 2,
        "_DisableGroupFiter": false,
        "_IsPrioryMysteryGroupTarget": false
      },
      {}
    ]
  }
}