{
  "app.user_data.HairAdjustParam": {
    "JointParamList": [
      {
        "IsEnable": true,
        "TargetJoint": "Hair_EX_01\u0000",
        "TargetJointNameHash": {
          "_Hash": 0
        },
        "Position": [
          0.0,
          0.0,
          0.0
        ],
        "Rotation": [
          0.0,
          0.0,
          0.0,
          1.0
        ],
        "Scale": [
          1.0,
          1.0,
          1.0
        ]
      },
      {
        "IsEnable": true,
        "TargetJoint": "Hair_EX_02\u0000",
        "TargetJointNameHash": {
          "_Hash": 0
        },
        "Position": [
          1.0884833e-8,
          0.0034759569,
          -7.727067e-9
        ],
        "Rotation": [
          0.0,
          0.0,
          0.0,
          1.0
        ],
        "Scale": [
          1.0,
          1.0,
          1.0
        ]
      },
      {
        "IsEnable": true,
        "TargetJoint": "Hair_EX_03\u0000",
        "TargetJointNameHash": {
          "_Hash": 0
        },
        "Position": [
          -1.9266736e-8,
          0.007272007,
          1.6603735e-8
        ],
        "Rotation": [
          0.0,
          0.0,
          0.0,
          1.0
        ],
        "Scale": [
          1.0,
          1.0,
          1.0
        ]
      },
      {
        "IsEnable": true,
        "TargetJoint": "Hair_EX_04\u0000",
        "TargetJointNameHash": {
          "_Hash": 0
        },
        "Position": [
          0.0,
          0.0,
          0.0
        ],
        "Rotation": [
          0.0,
          0.0,
          0.0,
          1.0
        ],
        "Scale": [
          1.0,
          1.0,
          1.0
        ]
      },
      {
        "IsEnable": true,
        "TargetJoint": "Hair_EX_05\u0000",
        "TargetJointNameHash": {
          "_Hash": 0
        },
        "Position": [
          -1.5444857e-7,
          -4.7480626e-8,
          0.0019389936
        ],
        "Rotation": [
          -1.1525117e-8,
          -5.9371814e-8,
          8.381903e-9,
          -0.9999999
        ],
        "Scale": [
          1.0,
          1.0,
          1.0
        ]
      },
      {
        "IsEnable": true,
        "TargetJoint": "Hair_EX_06\u0000",
        "TargetJointNameHash": {
          "_Hash": 0
        },
        "Position": [
          0.0,
          0.0,
          0.0
        ],
        "Rotation": [
          0.0,
          0.0,
          0.0,
          1.0
        ],
        "Scale": [
          1.0,
          1.0,
          1.0
        ]
      },
      {
        "IsEnable": true,
        "TargetJoint": "Hair_EX_07\u0000",
        "TargetJointNameHash": {
          "_Hash": 0
        },
        "Position": [
          0.0,
          0.0,
          0.0
        ],
        "Rotation": [
          0.0,
          0.0,
          0.0,
          1.0
        ],
        "Scale": [
          1.0,
          1.0,
          1.0
        ]
      },
      {
        "IsEnable": true,
        "TargetJoint": "Hair_EX_08\u0000",
        "TargetJointNameHash": {
          "_Hash": 0
        },
        "Position": [
          0.0,
          0.0,
          0.0
        ],
        "Rotation": [
          0.0,
          0.0,
          0.0,
          1.0
        ],
        "Scale": [
          1.0,
          1.0,
          1.0
        ]
      },
      {
        "IsEnable": true,
        "TargetJoint": "Hair_EX_09\u0000",
        "TargetJointNameHash": {
          "_Hash": 0
        },
        "Position": [
          0.0,
          0.0,
          0.0
        ],
        "Rotation": [
          0.0,
          0.0,
          0.0,
          1.0
        ],
        "Scale": [
          1.0,
          1.0,
          1.0
        ]
      },
      {
        "IsEnable": true,
        "TargetJoint": "Hair_EX_10\u0000",
        "TargetJointNameHash": {
          "_Hash": 0
        },
        "Position": [
          0.0,
          0.0,
          0.0
        ],
        "Rotation": [
          0.0,
          0.0,
          0.0,
          1.0
        ],
        "Scale": [
          1.0,
          1.0,
          1.0
        ]
      },
      {
        "IsEnable": true,
        "TargetJoint": "Hair_EX_11\u0000",
        "TargetJointNameHash": {
          "_Hash": 0
        },
        "Position": [
          0.0,
          0.0,
          0.0
        ],
        "Rotation": [
          0.0,
          0.0,
          0.0,
          1.0
        ],
        "Scale": [
          1.0,
          1.0,
          1.0
        ]
      },
      {
        "IsEnable": true,
        "TargetJoint": "Hair_EX_12\u0000",
        "TargetJointNameHash": {
          "_Hash": 0
        },
        "Position": [
          0.010473802,
          -0.0003404214,
          -0.0119076995
        ],
        "Rotation": [
          -0.10001488,
          -0.004239575,
          0.023132179,
          -0.994708
        ],
        "Scale": [
          0.94303817,
          0.91569597,
          1.0
        ]
      },
      {
        "IsEnable": true,
        "TargetJoint": "Hair_EX_13\u0000",
        "TargetJointNameHash": {
          "_Hash": 0
        },
        "Position": [
          -0.004711045,
          -4.089543e-8,
          -0.012091782
        ],
        "Rotation": [
          0.0,
          0.0,
          0.0,
          1.0
        ],
        "Scale": [
          0.5672605,
          1.0,
          1.0
        ]
      },
      {
        "IsEnable": true,
        "TargetJoint": "Hair_EX_14\u0000",
        "TargetJointNameHash": {
          "_Hash": 0
        },
        "Position": [
          -3.4458935e-8,
          0.01433068,
          -0.013234216
        ],
        "Rotation": [
          0.0,
          0.0,
          0.0,
          1.0
        ],
        "Scale": [
          1.0,
          1.0,
          1.0
        ]
      },
      {
        "IsEnable": true,
        "TargetJoint": "Hair_EX_15\u0000",
        "TargetJointNameHash": {
          "_Hash": 0
        },
        "Position": [
          -9.313226e-10,
          -1.3213139e-8,
          -0.0071716206
        ],
        "Rotation": [
          0.0,
          0.0,
          0.0,
          1.0
        ],
        "Scale": [
          1.0,
          1.0,
          1.0
        ]
      },
      {
        "IsEnable": true,
        "TargetJoint": "Hair_EX_16\u0000",
        "TargetJointNameHash": {
          "_Hash": 0
        },
        "Position": [
          3.7252903e-9,
          0.004609067,
          -0.019923568
        ],
        "Rotation": [
          0.0,
          0.0,
          0.0,
          1.0
        ],
        "Scale": [
          1.0,
          1.0,
          1.0
        ]
      },
      {
        "IsEnable": true,
        "TargetJoint": "Hair_EX_17\u0000",
        "TargetJointNameHash": {
          "_Hash": 0
        },
        "Position": [
          -5.5879354e-9,
          -3.085006e-8,
          -0.013598217
        ],
        "Rotation": [
          0.0,
          0.0,
          0.0,
          1.0
        ],
        "Scale": [
          1.0,
          1.0,
          1.0
        ]
      },
      {
        "IsEnable": true,
        "TargetJoint": "Hair_EX_18\u0000",
        "TargetJointNameHash": {
          "_Hash": 0
        },
        "Position": [
          -5.9604645e-8,
          0.011800799,
          -0.013200588
        ],
        "Rotation": [
          0.0,
          0.0,
          0.0,
          1.0
        ],
        "Scale": [
          1.0,
          1.0,
          1.0
        ]
      },
      {
        "IsEnable": true,
        "TargetJoint": "Hair_EX_19\u0000",
        "TargetJointNameHash": {
          "_Hash": 0
        },
        "Position": [
          0.006714728,
          6.920891e-8,
          -0.03608179
        ],
        "Rotation": [
          -0.18762833,
          1.5902333e-7,
          -5.9604645e-8,
          -0.98223996
        ],
        "Scale": [
          0.56856054,
          1.0,
          1.0
        ]
      },
      {
        "IsEnable": true,
        "TargetJoint": "Hair_EX_20\u0000",
        "TargetJointNameHash": {
          "_Hash": 0
        },
        "Position": [
          0.0,
          0.0,
          0.0
        ],
        "Rotation": [
          0.0,
          0.0,
          0.0,
          1.0
        ],
        "Scale": [
          1.0,
          1.0,
          1.0
        ]
      },
      {
        "IsEnable": true,
        "TargetJoint": "Hair_EX_21\u0000",
        "TargetJointNameHash": {
          "_Hash": 0
        },
        "Position": [
          0.0,
          0.0,
          0.0
        ],
        "Rotation": [
          0.0,
          0.0,
          0.0,
          1.0
        ],
        "Scale": [
          1.0,
          1.0,
          1.0
        ]
      },
      {
        "IsEnable": true,
        "TargetJoint": "Hair_EX_22\u0000",
        "TargetJointNameHash": {
          "_Hash": 0
        },
        "Position": [
          0.0,
          0.0,
          0.0
        ],
        "Rotation": [
          0.0,
          0.0,
          0.0,
          1.0
        ],
        "Scale": [
          1.0,
          1.0,
          1.0
        ]
      },
      {
        "IsEnable": true,
        "TargetJoint": "Hair_EX_23\u0000",
        "TargetJointNameHash": {
          "_Hash": 0
        },
        "Position": [
          0.0,
          0.0,
          0.0
        ],
        "Rotation": [
          0.0,
          0.0,
          0.0,
          1.0
        ],
        "Scale": [
          1.0,
          1.0,
          1.0
        ]
      },
      {
        "IsEnable": true,
        "TargetJoint": "Hair_EX_24\u0000",
        "TargetJointNameHash": {
          "_Hash": 0
        },
        "Position": [
          0.0,
          0.0,
          0.0
        ],
        "Rotation": [
          0.0,
          0.0,
          0.0,
          1.0
        ],
        "Scale": [
          1.0,
          1.0,
          1.0
        ]
      },
      {
        "IsEnable": true,
        "TargetJoint": "Hair_EX_25\u0000",
        "TargetJointNameHash": {
          "_Hash": 0
        },
        "Position": [
          0.0,
          0.0,
          0.0
        ],
        "Rotation": [
          0.0,
          0.0,
          0.0,
          1.0
        ],
        "Scale": [
          1.0,
          1.0,
          1.0
        ]
      },
      {
        "IsEnable": true,
        "TargetJoint": "Hair_EX_26\u0000",
        "TargetJointNameHash": {
          "_Hash": 0
        },
        "Position": [
          0.0,
          0.0,
          0.0
        ],
        "Rotation": [
          0.0,
          0.0,
          0.0,
          1.0
        ],
        "Scale": [
          1.0,
          1.0,
          1.0
        ]
      },
      {
        "IsEnable": true,
        "TargetJoint": "Hair_EX_27\u0000",
        "TargetJointNameHash": {
          "_Hash": 0
        },
        "Position": [
          0.0,
          0.0,
          0.0
        ],
        "Rotation": [
          0.0,
          0.0,
          0.0,
          1.0
        ],
        "Scale": [
          1.0,
          1.0,
          1.0
        ]
      },
      {
        "IsEnable": true,
        "TargetJoint": "Hair_EX_28\u0000",
        "TargetJointNameHash": {
          "_Hash": 0
        },
        "Position": [
          0.0,
          0.0,
          0.0
        ],
        "Rotation": [
          0.0,
          0.0,
          0.0,
          1.0
        ],
        "Scale": [
          1.0,
          1.0,
          1.0
        ]
      },
      {
        "IsEnable": true,
        "TargetJoint": "Hair_EX_29\u0000",
        "TargetJointNameHash": {
          "_Hash": 0
        },
        "Position": [
          0.0,
          0.0,
          0.0
        ],
        "Rotation": [
          0.0,
          0.0,
          0.0,
          1.0
        ],
        "Scale": [
          1.0,
          1.0,
          1.0
        ]
      },
      {
        "IsEnable": true,
        "TargetJoint": "Hair_EX_30\u0000",
        "TargetJointNameHash": {
          "_Hash": 0
        },
        "Position": [
          0.0,
          0.0,
          0.0
        ],
        "Rotation": [
          0.0,
          0.0,
          0.0,
          1.0
        ],
        "Scale": [
          1.0,
          1.0,
          1.0
        ]
      },
      {
        "IsEnable": true,
        "TargetJoint": "Hair_EX_31\u0000",
        "TargetJointNameHash": {
          "_Hash": 0
        },
        "Position": [
          0.0,
          0.0,
          0.0
        ],
        "Rotation": [
          0.0,
          0.0,
          0.0,
          1.0
        ],
        "Scale": [
          1.0,
          1.0,
          1.0
        ]
      }
    ],
    "_ChainParamList": [
      {
        "IsEnable": false,
        "ConstNodeNo": -1,
        "BlendRate": 1.0
      },
      {
        "IsEnable": true,
        "ConstNodeNo": -1,
        "BlendRate": 1.0
      },
      {
        "IsEnable": true,
        "ConstNodeNo": -1,
        "BlendRate": 1.0
      },
      {
        "IsEnable": true,
        "ConstNodeNo": -1,
        "BlendRate": 1.0
      },
      {
        "IsEnable": true,
        "ConstNodeNo": -1,
        "BlendRate": 1.0
      },
      {
        "IsEnable": true,
        "ConstNodeNo": -1,
        "BlendRate": 1.0
      },
      {
        "IsEnable": true,
        "ConstNodeNo": -1,
        "BlendRate": 1.0
      },
      {
        "IsEnable": true,
        "ConstNodeNo": -1,
        "BlendRate": 1.0
      },
      {
        "IsEnable": true,
        "ConstNodeNo": -1,
        "BlendRate": 1.0
      },
      {
        "IsEnable": true,
        "ConstNodeNo": -1,
        "BlendRate": 1.0
      },
      {
        "IsEnable": true,
        "ConstNodeNo": -1,
        "BlendRate": 1.0
      },
      {
        "IsEnable": true,
        "ConstNodeNo": -1,
        "BlendRate": 1.0
      },
      {
        "IsEnable": true,
        "ConstNodeNo": -1,
        "BlendRate": 1.0
      },
      {
        "IsEnable": true,
        "ConstNodeNo": -1,
        "BlendRate": 1.0
      }
    ],
    "ChainAllOff": false
  }
}