{
  "ace.user_data.EnumMaker": {
    "_DataList": [
      {
        "_EnumName": "INVALID\u0000",
        "_EnumValue": -1,
        "_FixedID": -1713811456
      },
      {
        "_EnumName": "START\u0000",
        "_EnumValue": 0,
        "_FixedID": -1801353216
      },
      {
        "_EnumName": "GOING\u0000",
        "_EnumValue": 1,
        "_FixedID": -1708281728
      },
      {
        "_EnumName": "WORK\u0000",
        "_EnumValue": 2,
        "_FixedID": -1465244032
      },
      {
        "_EnumName": "WORK_END\u0000",
        "_EnumValue": 3,
        "_FixedID": -1964061312
      },
      {
        "_EnumName": "GOING_2\u0000",
        "_EnumValue": 4,
        "_FixedID": -1185998336
      },
      {
        "_EnumName": "WORK_2\u0000",
        "_EnumValue": 5,
        "_FixedID": -799512064
      },
      {
        "_EnumName": "WORK_END_2\u0000",
        "_EnumValue": 6,
        "_FixedID": -605656448
      },
      {
        "_EnumName": "GOING_3\u0000",
        "_EnumValue": 7,
        "_FixedID": -492272384
      },
      {
        "_EnumName": "WORK_3\u0000",
        "_EnumValue": 8,
        "_FixedID": 319435584
      },
      {
        "_EnumName": "WORK_END_3\u0000",
        "_EnumValue": 9,
        "_FixedID": -2111579136
      },
      {
        "_EnumName": "RETURN\u0000",
        "_EnumValue": 10,
        "_FixedID": 256945680
      },
      {
        "_EnumName": "CAUTION\u0000",
        "_EnumValue": 11,
        "_FixedID": 29337
      },
      {
        "_EnumName": "TURN_BACK\u0000",
        "_EnumValue": 12,
        "_FixedID": 29586
      },
      {
        "_EnumName": "PANIC_GOING\u0000",
        "_EnumValue": 13,
        "_FixedID": 7334
      },
      {
        "_EnumName": "PANIC_ESCAPE\u0000",
        "_EnumValue": 14,
        "_FixedID": 20552
      },
      {
        "_EnumName": "PANIC_GOING_2\u0000",
        "_EnumValue": 15,
        "_FixedID": 13639
      },
      {
        "_EnumName": "PANIC_GOING_3\u0000",
        "_EnumValue": 16,
        "_FixedID": 22756
      },
      {
        "_EnumName": "PANIC_ESCAPE_3\u0000",
        "_EnumValue": 17,
        "_FixedID": 16365
      },
      {
        "_EnumName": "WARP_SHELTER\u0000",
        "_EnumValue": 18,
        "_FixedID": 11055
      }
    ],
    "_ExportNamespaceName": "app\u0000",
    "_ExportClassName": "NpcDef\u0000",
    "_ExportEnumName": "FIELD_UNIT_PHASE_UT105_01\u0000",
    "_EnumNameOfMaxElementCount": "MAX\u0000"
  }
}