{
  "app.user_data.CutsceneCutListData": {
    "_CutDataList": [
      {
        "CutNo": 0,
        "CutTotalFrame": 70.0,
        "StartFrame": 0.0,
        "EndFrame": 70.0,
        "StartCameraPos": [
          0.0,
          0.0,
          0.0
        ],
        "IsStartCameraPosManual": false
      },
      {
        "CutNo": 1,
        "CutTotalFrame": 1349.0,
        "StartFrame": 71.0,
        "EndFrame": 1420.0,
        "StartCameraPos": [
          0.0,
          0.0,
          0.0
        ],
        "IsStartCameraPosManual": false
      }
    ],
    "_IgnoreCutDataList": []
  }
}